web_observatory.py
web_observatory-1.2.3.dist-info/licenses/LICENSE
web_observatory-1.2.3.dist-info/WHEEL
web_observatory-1.2.3.dist-info/METADATA
web_observatory-1.2.3.dist-info/RECORD
