Metadata-Version: 2.4
Name: web-observatory
Version: 1.2.3
Summary: Python package for collecting and analyzing webpages
Author-email: Eric Nost <enost@uoguelph.ca>
Requires-Python: >=3.8
Classifier: Programming Language :: Python :: 3
Classifier: License :: OSI Approved :: GNU General Public License v3 (GPLv3)
Classifier: Operating System :: OS Independent
License-File: LICENSE
Requires-Dist: google_api_python_client==2.44.0
Requires-Dist: items==0.6.5
Requires-Dist: pandas>=1.3.4
Requires-Dist: psycopg2==2.8.6
Requires-Dist: Requests==2.31.0
Requires-Dist: Scrapy==2.6.1
Requires-Dist: tldextract==3.2.0
Requires-Dist: wayback>=0.3.2
Requires-Dist: pyopenssl==22.0.0
Requires-Dist: cryptography<38
Requires-Dist: Twisted==22.10.0
Project-URL: Homepage, https://github.com/ericnost/observatory
Project-URL: Issues, https://github.com/ericnost/observatory/issues
